geode_parameterization/Geode-Parameterization_frame_field.dll
geode_parameterization/Geode-Parameterization_scalar_function.dll
geode_parameterization/Geode-Parameterization_surface.dll
geode_parameterization/__init__.py
geode_parameterization/concrt140.dll
geode_parameterization/geode_parameterization_py_scalar_function.pyd
geode_parameterization/geode_parameterization_py_surface.pyd
geode_parameterization/msvcp140.dll
geode_parameterization/msvcp140_1.dll
geode_parameterization/msvcp140_2.dll
geode_parameterization/msvcp140_atomic_wait.dll
geode_parameterization/msvcp140_codecvt_ids.dll
geode_parameterization/scalar_function.py
geode_parameterization/surface.py
geode_parameterization/vcruntime140.dll
geode_parameterization/vcruntime140_1.dll
Geode_Parameterization-1.16.8.dist-info/METADATA
Geode_Parameterization-1.16.8.dist-info/WHEEL
Geode_Parameterization-1.16.8.dist-info/top_level.txt
Geode_Parameterization-1.16.8.dist-info/RECORD
