Metadata-Version: 2.1
Name: Geode-Parameterization
Version: 1.16.8
Summary: Parameterization algorithm module
Home-page: https://github.com/Geode-solutions/Geode-Parameterization
Author: Geode-solutions
Author-email: contact@geode-solutions.com
License: Proprietary
Platform: UNKNOWN
Requires-Dist: OpenGeode-core (==13.*,>=13.0.0)
Requires-Dist: Geode-Common (==24.*,>=24.0.0)
